zope.app.appsetup-5.1-py3.12-nspkg.pth
zope/app/appsetup/__init__.py
zope/app/appsetup/appsetup.py
zope/app/appsetup/bootstrap.py
zope/app/appsetup/bootstrap.rst
zope/app/appsetup/configure.zcml
zope/app/appsetup/controller.py
zope/app/appsetup/debug.py
zope/app/appsetup/debug.rst
zope/app/appsetup/errorlog.py
zope/app/appsetup/ftesting.zcml
zope/app/appsetup/interfaces.py
zope/app/appsetup/product.py
zope/app/appsetup/product.rst
zope/app/appsetup/session.py
zope/app/appsetup/testlayer.py
zope/app/appsetup/testlayer.rst
zope/app/appsetup/tests.py
zope/app/appsetup/schema/productconfig.xml
zope/app/appsetup/schema/schema.xml
zope/app/appsetup/testdata/pythonstartup.py
zope/app/appsetup/testdata/site.zcml
zope/app/appsetup/testdata/test.conf.txt
zope/app/appsetup/testpackage/__init__.py
zope/app/appsetup/testpackage/ftesting.zcml
zope/app/appsetup/testpackage/testobject.py
zope/app/appsetup/testproduct/__init__.py
zope/app/appsetup/testproduct/component.xml
zope_app_appsetup-5.1.dist-info/licenses/LICENSE.txt
zope_app_appsetup-5.1.dist-info/METADATA
zope_app_appsetup-5.1.dist-info/WHEEL
zope_app_appsetup-5.1.dist-info/entry_points.txt
zope_app_appsetup-5.1.dist-info/namespace_packages.txt
zope_app_appsetup-5.1.dist-info/top_level.txt
zope_app_appsetup-5.1.dist-info/RECORD
