Metadata-Version: 2.4
Name: zope.app.appsetup
Version: 5.1
Summary: Zope app setup helper
Home-page: https://github.com/zopefoundation/zope.app.appsetup
Author: Zope Foundation and Contributors
Author-email: zope-dev@zope.dev
License: ZPL-2.1
Keywords: zope3 app setup
Classifier: Development Status :: 5 - Production/Stable
Classifier: Environment :: Web Environment
Classifier: Intended Audience :: Developers
Classifier: License :: OSI Approved :: Zope Public License
Classifier: Programming Language :: Python :: 3
Classifier: Programming Language :: Python :: 3.9
Classifier: Programming Language :: Python :: 3.10
Classifier: Programming Language :: Python :: 3.11
Classifier: Programming Language :: Python :: 3.12
Classifier: Programming Language :: Python :: 3.13
Classifier: Programming Language :: Python :: Implementation
Classifier: Programming Language :: Python :: Implementation :: CPython
Classifier: Programming Language :: Python :: Implementation :: PyPy
Classifier: Natural Language :: English
Classifier: Operating System :: OS Independent
Classifier: Topic :: Internet :: WWW/HTTP
Classifier: Framework :: Zope :: 3
Requires-Python: >=3.9
License-File: LICENSE.txt
Requires-Dist: ZODB
Requires-Dist: zdaemon
Requires-Dist: setuptools
Requires-Dist: zope.app.publication>=4.0
Requires-Dist: zope.component>=3.8.0
Requires-Dist: zope.configuration
Requires-Dist: zope.container>=4.0.0a2
Requires-Dist: zope.error
Requires-Dist: zope.event
Requires-Dist: zope.interface
Requires-Dist: zope.processlifetime
Requires-Dist: zope.security>=4.0.0a2
Requires-Dist: zope.session>=4.0.0a1
Requires-Dist: zope.site>=4.0.0a1
Requires-Dist: zope.traversing>=4.0.0a2
Provides-Extra: test
Requires-Dist: zope.componentvocabulary>=2.0.0a1; extra == "test"
Requires-Dist: zope.principalregistry>=4.0.0a1; extra == "test"
Requires-Dist: zope.testing>=3.10; extra == "test"
Requires-Dist: zope.testrunner; extra == "test"
Dynamic: author
Dynamic: author-email
Dynamic: classifier
Dynamic: description
Dynamic: home-page
Dynamic: keywords
Dynamic: license
Dynamic: license-file
Dynamic: provides-extra
Dynamic: requires-dist
Dynamic: requires-python
Dynamic: summary
